textbot/__init__.py
textbot/__main__.py
textbot/csv_ops.py
textbot/pos_count.py
textbot/pos_tag.py
textbot/select_filename.py
textbot-0.1.0.dist-info/DESCRIPTION.rst
textbot-0.1.0.dist-info/METADATA
textbot-0.1.0.dist-info/RECORD
textbot-0.1.0.dist-info/WHEEL
textbot-0.1.0.dist-info/metadata.json
textbot-0.1.0.dist-info/top_level.txt
