Metadata-Version: 2.0
Name: textbot
Version: 0.1.0
Summary: Read a column of strings from csv, parse wordnet pos_tags to lemmas, enumerate most_common lemmas, weight strings via top scoring lemmas
Home-page: http://github.com/3pin/textbot
Author: 3pin
Author-email: 3pin.audiovisual@gmail.com
License: LICENSE.txt
Keywords: NLP,IE,wordnet,nltk
Platform: UNKNOWN
Classifier: Programming Language :: Python
Classifier: Programming Language :: Python :: 3
Classifier: Development Status :: 3 - Alpha
Classifier: Environment :: Console
Classifier: Intended Audience :: Developers
Classifier: Intended Audience :: Science/Research
Classifier: License :: OSI Approved :: GNU General Public License v3 (GPLv3)
Classifier: Operating System :: OS Independent
Classifier: Topic :: Software Development :: Libraries :: Python Modules
Classifier: Topic :: Text Processing :: Linguistic
Classifier: Topic :: Scientific/Engineering :: Information Analysis
Classifier: Topic :: Text Processing :: Linguistic
Classifier: Topic :: Text Processing :: Filters
Classifier: Topic :: Text Processing :: General
Requires-Python: >=3
Requires-Dist: UnicodeDammit
Requires-Dist: bs4
Requires-Dist: collections
Requires-Dist: json
Requires-Dist: nltk
Requires-Dist: operator
Requires-Dist: pandas
Requires-Dist: re
Requires-Dist: string
Requires-Dist: tkinter.filedialog
Requires-Dist: tkinter.simpledialog
